checkevenoddtool.py
checkevenoddtool-0.1.0.dist-info/METADATA
checkevenoddtool-0.1.0.dist-info/WHEEL
checkevenoddtool-0.1.0.dist-info/top_level.txt
checkevenoddtool-0.1.0.dist-info/RECORD
