Metadata-Version: 2.4
Name: checkevenoddtool
Version: 0.1.0
Summary: check if input is even or odd
Requires-Python: >=3.8
